scDiffusion/__init__.py
scDiffusion/diffusion/__init__.py
scDiffusion/diffusion/feature_encoder.py
scDiffusion/diffusion/gnd.py
scDiffusion/diffusion/graph_DIF.py
scDiffusion/sc_analysis/__init__.py
scDiffusion/sc_analysis/annotation.py
scDiffusion/sc_analysis/clustering.py
scDiffusion/sc_analysis/preprocess.py
scDiffusion/sc_analysis/trajectory.py
scDiffusion/sc_analysis/trajectory_plot.py
scDiffusion/sc_graph/__init__.py
scDiffusion/sc_graph/build_graph.py
scDiffusion/sc_graph/graph_attention.py
scDiffusion/sc_graph/graph_modularity.py
scDiffusion/sc_integration/Harmony.py
scDiffusion/sc_integration/__init__.py
scDiffusion/sc_integration/integration_DIF.py
scDiffusion/sc_integration/integration_graph.py
scDiffusion/utils/__init__.py
scDiffusion/utils/info_log.py
scDiffusion/utils/umap_fn.py
scDiffusion/utils/utility_fn.py
scDiffusion-0.8.dist-info/METADATA
scDiffusion-0.8.dist-info/WHEEL
scDiffusion-0.8.dist-info/top_level.txt
scDiffusion-0.8.dist-info/RECORD
